{
  "pages": [
    {
      "title": "Home",
      "href": "/",
      "id": ""
    },
    {
      "title": "Services",
      "href": "/",
      "id": "services"
    },
    {
      "title": "Blog",
      "href": "/blog",
      "id": ""
    }
  ],
  "legal": [
    {
      "title": "Privacy Policy",
      "href": "/privacy-policy",
      "id": ""
    },
    {
      "title": "Terms & Conditions",
      "href": "/terms",
      "id": ""
    }
  ],
  "contact": [
    {
      "title": "Email us at info@navillus.dev",
      "url": "mailto:info@navillus.dev",
      "icon": "email"
    },
    {
      "title": "Find us on Twitter",
      "url": "https://twitter.com/navillus_dev",
      "icon": "twitter"
    },
    {
      "title": "Find us on dev.to",
      "url": "https://dev.to/navillus_dev",
      "icon": "devto"
    },
    {
      "title": "Find us on Github",
      "url": "https://github.com/navillus-dev",
      "icon": "github"
    },
    {
      "title": "RSS Feed",
      "url": "https://navillus.dev/feed/blog.xml",
      "icon": "rss"
    }
  ]
}
